Metadata-Version: 2.1
Name: AegosLib
Version: 0.1
Summary: Checking emails for any domain , for example : gmail,yahoo,aol,hotmail,outlook,mail_ru
Author: Aegos
Author-email: syakkml@gmail.com
Classifier: Programming Language :: Python :: 3
Classifier: Operating System :: OS Independent
Classifier: License :: OSI Approved :: MIT License
License-File: LICENSE.txt
